up_social_laws/__init__.py
up_social_laws/ma_centralizer.py
up_social_laws/ma_problem_waitfor.py
up_social_laws/robustness_checker.py
up_social_laws/robustness_verification.py
up_social_laws/sa_to_ma_converter.py
up_social_laws/single_agent_projection.py
up_social_laws/social_law.py
up_social_laws/synthesis.py
up_social_laws/waitfor_specification.py
up_social_laws-0.2.0.dist-info/LICENSE
up_social_laws-0.2.0.dist-info/METADATA
up_social_laws-0.2.0.dist-info/WHEEL
up_social_laws-0.2.0.dist-info/top_level.txt
up_social_laws-0.2.0.dist-info/RECORD
